AUTHORS.rst
CONTRIBUTING.rst
HISTORY.rst
LICENSE.txt
MANIFEST.in
README.rst
setup.cfg
setup.py
versioneer.py
docs/Makefile
docs/api.rst
docs/authors.rst
docs/conf.py
docs/contributing.rst
docs/history.rst
docs/index.rst
docs/installation.rst
docs/make.bat
docs/readme.rst
docs/usage.rst
imgroi/__init__.py
imgroi/_version.py
imgroi/core.py
imgroi.egg-info/PKG-INFO
imgroi.egg-info/SOURCES.txt
imgroi.egg-info/dependency_links.txt
imgroi.egg-info/not-zip-safe
imgroi.egg-info/requires.txt
imgroi.egg-info/top_level.txt
tests/__init__.py
tests/test_core.py